rxn/chemutils/__init__.py
rxn/chemutils/conversion.py
rxn/chemutils/exceptions.py
rxn/chemutils/extended_reaction_smiles.py
rxn/chemutils/miscellaneous.py
rxn/chemutils/multicomponent_smiles.py
rxn/chemutils/py.typed
rxn/chemutils/rdkit_utils.py
rxn/chemutils/reaction_combiner.py
rxn/chemutils/reaction_equation.py
rxn/chemutils/reaction_smiles.py
rxn/chemutils/smiles_augmenter.py
rxn/chemutils/smiles_randomization.py
rxn/chemutils/smiles_standardization.py
rxn/chemutils/tokenization.py
rxn/chemutils/utils.py
rxn/chemutils/rdf/__init__.py
rxn/chemutils/rdf/property_parser.py
rxn/chemutils/rdf/rdf_parser.py
rxn/chemutils/rdf/rdf_reaction.py
rxn/chemutils/rdf/reaction_properties.py
rxn/chemutils/rdf/reaction_smiles_extractor.py
rxn/chemutils/scripts/__init__.py
rxn/chemutils/scripts/canonicalize.py
rxn/chemutils/scripts/combine_reaction.py
rxn/chemutils/scripts/detokenize.py
rxn/chemutils/scripts/rdf_to_smiles.py
rxn/chemutils/scripts/tokenize.py
rxn_chem_utils-1.6.0.dist-info/LICENSE
rxn_chem_utils-1.6.0.dist-info/METADATA
rxn_chem_utils-1.6.0.dist-info/WHEEL
rxn_chem_utils-1.6.0.dist-info/entry_points.txt
rxn_chem_utils-1.6.0.dist-info/top_level.txt
rxn_chem_utils-1.6.0.dist-info/RECORD
