Metadata-Version: 2.1
Name: rxn-chem-utils
Version: 1.6.0
Summary: Chemistry-related utilities
Author: IBM RXN team
Author-email: rxn4chemistry@zurich.ibm.com
License: MIT
Classifier: Operating System :: OS Independent
Classifier: Programming Language :: Python :: 3
Classifier: Programming Language :: Python :: 3.7
Classifier: Programming Language :: Python :: 3.8
Classifier: Programming Language :: Python :: 3.9
Classifier: Programming Language :: Python :: 3.10
Classifier: Programming Language :: Python :: 3.11
Requires-Python: >=3.7
License-File: LICENSE
Requires-Dist: attrs >=21.2.0
Requires-Dist: click >=7.0
Requires-Dist: rxn-utils >=1.1.9
Provides-Extra: dev
Requires-Dist: black >=22.3.0 ; extra == 'dev'
Requires-Dist: bump2version >=1.0.1 ; extra == 'dev'
Requires-Dist: flake8 >=3.7.9 ; extra == 'dev'
Requires-Dist: isort >=5.9.3 ; extra == 'dev'
Requires-Dist: mypy >=0.910 ; extra == 'dev'
Requires-Dist: pytest >=5.3.4 ; extra == 'dev'
Requires-Dist: types-setuptools >=57.4.17 ; extra == 'dev'
Provides-Extra: rdkit
Requires-Dist: rdkit >=2022.3.4 ; extra == 'rdkit'
